roommates/__init__.py
roommates-0.1.0.dist-info/LICENSE
roommates-0.1.0.dist-info/METADATA
roommates-0.1.0.dist-info/WHEEL
roommates-0.1.0.dist-info/top_level.txt
roommates-0.1.0.dist-info/RECORD
