Metadata-Version: 2.1
Name: roommates
Version: 0.1.0
Summary: Compute equalization payments
Home-page: https://github.com/MDAddario/roommates
Author: Michael Lindner-D'Addario
Author-email: michael.lindner.daddario@gmail.com
License: UNKNOWN
Platform: UNKNOWN
Classifier: Programming Language :: Python :: 3
Classifier: License :: OSI Approved :: MIT License
Classifier: Operating System :: OS Independent
Requires-Python: >=3.6
